<annotation>
	<folder>output</folder>
	<filename>sample24-40.jpg</filename>
	<path>/Users/surajs/Downloads/output/sample24-40.jpg</path>
	<source>
		<database>Unknown</database>
	</source>
	<size>
		<width>1280</width>
		<height>720</height>
		<depth>3</depth>
	</size>
	<segmented>0</segmented>
	<object>
		<name>ui</name>
		<pose>Unspecified</pose>
		<truncated>0</truncated>
		<difficult>0</difficult>
		<bndbox>
			<xmin>359</xmin>
			<ymin>297</ymin>
			<xmax>519</xmax>
			<ymax>446</ymax>
		</bndbox>
	</object>
	<object>
		<name>arrow</name>
		<pose>Unspecified</pose>
		<truncated>0</truncated>
		<difficult>0</difficult>
		<bndbox>
			<xmin>519</xmin>
			<ymin>345</ymin>
			<xmax>650</xmax>
			<ymax>413</ymax>
		</bndbox>
	</object>
	<object>
		<name>ec2</name>
		<pose>Unspecified</pose>
		<truncated>0</truncated>
		<difficult>0</difficult>
		<bndbox>
			<xmin>648</xmin>
			<ymin>299</ymin>
			<xmax>785</xmax>
			<ymax>442</ymax>
		</bndbox>
	</object>
</annotation>
